main.py
uniswap_poolspy_mcp-0.1.0.dist-info/licenses/LICENSE
uniswap_poolspy_mcp-0.1.0.dist-info/METADATA
uniswap_poolspy_mcp-0.1.0.dist-info/WHEEL
uniswap_poolspy_mcp-0.1.0.dist-info/top_level.txt
uniswap_poolspy_mcp-0.1.0.dist-info/RECORD
