Metadata-Version: 2.4
Name: uniswap-poolspy-mcp
Version: 0.1.0
Summary: An MCP server that tracks newly created liquidity pools on Uniswap across nine blockchain networks
Requires-Python: >=3.13
License-File: LICENSE
Requires-Dist: httpx>=0.28.1
Requires-Dist: mcp[cli]>=1.4.1
Dynamic: license-file
